{
  "version": "training-job-contract-v1",
  "go_training_env_keys": [
    "TRAINING_ADAPTER_URI",
    "TRAINING_ARTIFACT_BUCKET_REGION",
    "TRAINING_ARTIFACT_FORMAT",
    "TRAINING_ARTIFACT_MANIFEST_URI",
    "TRAINING_AXOLOTL_COMMAND",
    "TRAINING_BASE_MODEL",
    "TRAINING_DATASET_URI",
    "TRAINING_MODEL_NAME",
    "TRAINING_MODEL_URI",
    "TRAINING_MODEL_VERSION",
    "TRAINING_RECIPE_HASH",
    "TRAINING_RECIPE_YAML",
    "TRAINING_RUN_ID",
    "TRAINING_SERVING_LOAD_STATUS",
    "TRAINING_SERVING_MODEL",
    "TRAINING_SERVING_TARGET"
  ],
  "go_evaluation_env_keys": [
    "TRAINING_ARTIFACT_BUCKET_REGION",
    "TRAINING_EVALUATION_MANIFEST_URI",
    "TRAINING_EVALUATION_PROFILE",
    "TRAINING_EVALUATION_REPORT_URI",
    "TRAINING_MODEL_URI",
    "TRAINING_RUN_ID"
  ],
  "go_promotion_env_keys": [
    "TRAINING_ARTIFACT_BUCKET_REGION"
  ],
  "python_training_required_env_keys": [
    "TRAINING_ARTIFACT_MANIFEST_URI",
    "TRAINING_AXOLOTL_COMMAND",
    "TRAINING_BASE_MODEL",
    "TRAINING_MODEL_NAME",
    "TRAINING_MODEL_URI",
    "TRAINING_MODEL_VERSION",
    "TRAINING_RECIPE_YAML",
    "TRAINING_RUN_ID"
  ],
  "python_training_optional_env_keys": [
    "TRAINING_ADAPTER_URI",
    "TRAINING_ARTIFACT_FORMAT",
    "TRAINING_JOB_WORK_DIR",
    "TRAINING_RECIPE_HASH",
    "TRAINING_SERVING_LOAD_STATUS",
    "TRAINING_SERVING_MODEL",
    "TRAINING_SERVING_TARGET"
  ],
  "python_evaluation_required_env_keys": [
    "TRAINING_EVALUATION_MANIFEST_URI",
    "TRAINING_EVALUATION_PROFILE",
    "TRAINING_EVALUATION_REPORT_URI",
    "TRAINING_MODEL_URI",
    "TRAINING_RUN_ID"
  ],
  "python_evaluation_optional_env_keys": [
    "TRAINING_EVALUATION_COMMAND",
    "TRAINING_JOB_WORK_DIR"
  ],
  "python_promotion_required_env_keys": [],
  "python_promotion_optional_env_keys": [
    "TRAINING_ARTIFACT_BUCKET_REGION",
    "TRAINING_JOB_WORK_DIR"
  ],
  "promotion_job_spec_keys": [
    "candidate_metrics_metadata",
    "candidate_report_uri",
    "model_id",
    "promotion_profile",
    "report_manifest_uri",
    "report_uri",
    "training_run_id",
    "user_id"
  ],
  "promotion_optional_job_spec_keys": [
    "champion_metrics_metadata",
    "champion_model_id",
    "champion_report_uri"
  ],
  "env_key_contract": {
    "TRAINING_ADAPTER_URI": {"direction": "go_to_python", "type": "string"},
    "TRAINING_ARTIFACT_BUCKET_REGION": {"direction": "go_to_python", "type": "string"},
    "TRAINING_ARTIFACT_FORMAT": {"direction": "go_to_python", "type": "string"},
    "TRAINING_ARTIFACT_MANIFEST_URI": {"direction": "go_to_python", "type": "string"},
    "TRAINING_AXOLOTL_COMMAND": {"direction": "go_to_python", "type": "string"},
    "TRAINING_BASE_MODEL": {"direction": "go_to_python", "type": "string"},
    "TRAINING_DATASET_URI": {"direction": "go_to_python", "type": "string"},
    "TRAINING_EVALUATION_COMMAND": {"direction": "runtime_to_python", "type": "string"},
    "TRAINING_EVALUATION_MANIFEST_URI": {"direction": "go_to_python", "type": "string"},
    "TRAINING_EVALUATION_PROFILE": {"direction": "go_to_python", "type": "string"},
    "TRAINING_EVALUATION_REPORT_URI": {"direction": "go_to_python", "type": "string"},
    "TRAINING_JOB_WORK_DIR": {"direction": "runtime_to_python", "type": "string"},
    "TRAINING_MODEL_NAME": {"direction": "go_to_python", "type": "string"},
    "TRAINING_MODEL_URI": {"direction": "go_to_python", "type": "string"},
    "TRAINING_MODEL_VERSION": {"direction": "go_to_python", "type": "string"},
    "TRAINING_RECIPE_HASH": {"direction": "go_to_python", "type": "string"},
    "TRAINING_RECIPE_YAML": {"direction": "go_to_python", "type": "string"},
    "TRAINING_RUN_ID": {"direction": "go_to_python", "type": "string"},
    "TRAINING_SERVING_LOAD_STATUS": {"direction": "go_to_python", "type": "string"},
    "TRAINING_SERVING_MODEL": {"direction": "go_to_python", "type": "string"},
    "TRAINING_SERVING_TARGET": {"direction": "go_to_python", "type": "string"}
  },
  "training_manifest_keys": [
    "adapter_uri",
    "artifact_checksum",
    "artifact_format",
    "artifact_size_bytes",
    "base_model",
    "model_name",
    "model_uri",
    "model_version",
    "recipe_hash",
    "serving_load_status",
    "serving_model",
    "serving_target",
    "training_run_id"
  ],
  "evaluation_manifest_keys": [
    "deepchecks_passed",
    "deepchecks_report_uri",
    "eval_dataset_mode",
    "eval_dataset_uri",
    "evaluator_name",
    "evaluator_version",
    "evidently_passed",
    "evidently_report_uri",
    "failure_reason",
    "judge_model",
    "judge_provider",
    "judge_template_version",
    "metric_suite",
    "metrics",
    "passed",
    "report_uri",
    "score_rows_uri",
    "thresholds",
    "training_run_id"
  ],
  "training_manifest_field_types": {
    "adapter_uri": "string",
    "artifact_checksum": "string",
    "artifact_format": "string",
    "artifact_size_bytes": "int64",
    "base_model": "string",
    "model_name": "string",
    "model_uri": "string",
    "model_version": "string",
    "recipe_hash": "string",
    "serving_load_status": "string",
    "serving_model": "string",
    "serving_target": "string",
    "training_run_id": "string"
  },
  "evaluation_manifest_field_types": {
    "deepchecks_passed": "bool",
    "deepchecks_report_uri": "string",
    "eval_dataset_mode": "string",
    "eval_dataset_uri": "string",
    "evidently_passed": "bool",
    "evidently_report_uri": "string",
    "evaluator_name": "string",
    "evaluator_version": "string",
    "failure_reason": "string",
    "judge_model": "string",
    "judge_provider": "string",
    "judge_template_version": "string",
    "metric_suite": "string",
    "metrics": "map_string_float64",
    "passed": "bool",
    "report_uri": "string",
    "score_rows_uri": "string",
    "thresholds": "map_string_float64",
    "training_run_id": "string"
  },
  "promotion_manifest_keys": [
    "deepchecks_passed",
    "deepchecks_report_uri",
    "deltas",
    "evidently_passed",
    "evidently_report_uri",
    "failure_reason",
    "model_id",
    "promotion_report_uri",
    "training_run_id",
    "user_id"
  ],
  "promotion_manifest_field_types": {
    "deepchecks_passed": "bool",
    "deepchecks_report_uri": "string",
    "deltas": "map_string_float64",
    "evidently_passed": "bool",
    "evidently_report_uri": "string",
    "failure_reason": "string",
    "model_id": "string",
    "promotion_report_uri": "string",
    "training_run_id": "string",
    "user_id": "string"
  }
}
